fas14mnet/__init__.py
fas14mnet/core.py
fas14mnet/net.py
Fas14MNet-0.1.2.dist-info/LICENSE.txt
Fas14MNet-0.1.2.dist-info/METADATA
Fas14MNet-0.1.2.dist-info/WHEEL
Fas14MNet-0.1.2.dist-info/top_level.txt
Fas14MNet-0.1.2.dist-info/RECORD
