Metadata-Version: 2.1
Name: Fas14MNet
Version: 0.1.2
Summary: CNN architecture for Image Classification
Home-page: https://github.com/DigantaD/Fas14MNet/tree/main/src
Author: Sonali Saha, Diganta Dutta
Author-email: sonalisaha2310@gmail.com, diganta.aimlos@gmail.com
License: UNKNOWN
Keywords: image classification,cnn
Platform: UNKNOWN
Classifier: Development Status :: 5 - Production/Stable
Classifier: Intended Audience :: Developers
Classifier: Programming Language :: Python :: 3
Classifier: Operating System :: Unix
Classifier: Operating System :: MacOS :: MacOS X
Classifier: Operating System :: Microsoft :: Windows
Requires-Dist: torch
